demo_package_sample_data_with_code/__init__.py
demo_package_sample_data_with_code/__main__.py
demo_package_sample_data_with_code/__version__.py
demo_package_sample_data_with_code/constants.py
demo_package_sample_data_with_code/my_module.py
demo_package_sample_data_with_code/sample_data_pi.txt
demo_package_sample_data_with_code/sample_data/.DS_Store
demo_package_sample_data_with_code/sample_data/__init__.py
demo_package_sample_data_with_code/sample_data/sample_data_e.txt
demo_package_sample_data_with_code/sample_data/__pycache__/__init__.cpython-39.pyc
demo_package_sample_data_with_code-1.0.3.dist-info/LICENSE
demo_package_sample_data_with_code-1.0.3.dist-info/METADATA
demo_package_sample_data_with_code-1.0.3.dist-info/WHEEL
demo_package_sample_data_with_code-1.0.3.dist-info/entry_points.txt
demo_package_sample_data_with_code-1.0.3.dist-info/top_level.txt
demo_package_sample_data_with_code-1.0.3.dist-info/RECORD
