Metadata-Version: 2.1
Name: demo-package-sample-data-with-code
Version: 1.0.3
Summary: Example of PyPI-submittable project that properly reads packaged static text files
Home-page: https://github.com/jimratliff/python-demo-package-sample-data-with-code
Author: Jim Ratliff
Author-email: jim@jim-ratliff.name
Project-URL: Bug Tracker, https://github.com/jimratliff/python-demo-package-sample-data-with-code/issues
Classifier: Programming Language :: Python :: 3.9
Classifier: License :: OSI Approved :: MIT License
Classifier: Operating System :: OS Independent
Classifier: Intended Audience :: Developers
Requires-Python: >=3.9
License-File: LICENSE
Requires-Dist: yachalk
